tests/__init__.py
tests/test_dmrg.py
tests/test_dmrg_u1.py
ttnopt/__init__.py
ttnopt/factorize_tensor.py
ttnopt/ground_state_search.py
ttnopt/hamiltonian.py
ttnopt/src/DataEngine.py
ttnopt/src/FactorizeTensor.py
ttnopt/src/GroundStateSearch.py
ttnopt/src/GroundStateSearchSparse.py
ttnopt/src/Hamiltonian.py
ttnopt/src/Observable.py
ttnopt/src/PhysicsEngine.py
ttnopt/src/PhysicsEngineSparse.py
ttnopt/src/TTN.py
ttnopt/src/TimeEvolution.py
ttnopt/src/TwoSiteUpdater.py
ttnopt/src/TwoSiteUpdaterSparse.py
ttnopt/src/__init__.py
ttnopt/src/functionTTN.py
ttnopt/src/initialTTN.py
ttnopt-0.1.0.dist-info/licenses/LICENSE
ttnopt-0.1.0.dist-info/METADATA
ttnopt-0.1.0.dist-info/WHEEL
ttnopt-0.1.0.dist-info/entry_points.txt
ttnopt-0.1.0.dist-info/top_level.txt
ttnopt-0.1.0.dist-info/RECORD
